node2vec/__init__.py
node2vec/edges.py
node2vec/node2vec.py
node2vec/parallel.py
node2vec/setup.cfg
node2vec-0.4.5.dist-info/LICENSE
node2vec-0.4.5.dist-info/WHEEL
node2vec-0.4.5.dist-info/METADATA
node2vec-0.4.5.dist-info/RECORD
